autobricks/Cluster.py
autobricks/Dbfs.py
autobricks/Job.py
autobricks/Library.py
autobricks/Pipeline.py
autobricks/SetupTools.py
autobricks/Sql.py
autobricks/Workspace.py
autobricks/_common.py
autobricks/_decode_utils.py
autobricks/api_service/__init__.py
autobricks/api_service/_auth.py
autobricks/api_service/_auth_factory.py
autobricks/api_service/_base_api.py
autobricks/api_service/_configuration.py
autobricks/api_service/_exceptions.py
autobricks/api_service/api_service.py
autobricks/api_service/autobricks_logging.py
autobricks-0.9.0.dist-info/METADATA
autobricks-0.9.0.dist-info/WHEEL
autobricks-0.9.0.dist-info/top_level.txt
autobricks-0.9.0.dist-info/RECORD
