Metadata-Version: 2.1
Name: autobricks
Version: 0.9.0
Summary: Databricks Deployment Utils
Home-page: https://autobricks.readthedocs.io/en/latest/
Author: Shaun Ryan
Author-email: shaun_chiburi@hotmail.com
License: MIT
Project-URL: GitHub, https://github.com/semanticinsight/autobricks
Project-URL: Documentation, https://autobricks.readthedocs.io/en/latest/
Classifier: License :: OSI Approved :: MIT License
Classifier: Programming Language :: Python :: 3
Classifier: Programming Language :: Python :: 3.8
Requires-Dist: requests
Requires-Dist: PyYAML
Requires-Dist: adal
